{
  "date": "2024-10-02",
  "dayAr": "الأربعاء",
  "dateAr": "٢ تشرين الأول ٢٠٢٤",
  "hijri": "٢٨ ربيع الأول ١٤٤٦ هـ.",
  "stats": {
    "b": 29,
    "s": 45,
    "e": 29,
    "ir": 2,
    "v": 0,
    "al": 1
  },
  "bayanat": [
    {
      "num": 0,
      "postTime": "03:49",
      "opTime": "",
      "target": "العديسة من جهة خلة المحافر واشتبكوا معها وأوقعوا بها خسائر",
      "weapon": "",
      "badge": "",
      "tags": [],
      "fullText": "1\n\nبيان صادر عن المقاومة الإسلامية: \n \nبِسْمِ اللَّـهِ الرحمن الرَّحِيمِ \n﴿أُذِنَ لِلَّذِينَ يُقَاتَلُونَ بِأَنَّهُمْ ظُلِمُوا وَإِنَّ اللَّهَ على نَصْرِهِمْ لَقَدِيرٌ﴾ \nصدق الله العلي العظيم \n \nدعماً لشعبنا الفلسطيني الصامد في قطاع غزة وإسناداً لمقاومته الباسلة ‌‏‌‏‌والشريفة، ودفاعًا عن لبنان ‏وشعبه، تصدى مجاهدو المقاومة ‏الإسلامية عند فجر يوم الأربعاء 2-10-2024 لِقوة من مشاة العدو الإسرائيلي حاولت التسلل إلى بلدة العديسة من جهة خلة المحافر واشتبكوا معها وأوقعوا بها خسائر وأجبروها على التراجع.  \n \n﴿وَمَا النَّصْرُ إِلاَّ مِنْ عِندِ اللّهِ الْعَزِيزِ الْحَكِيم﴾ \nالأربعاء 2-10-2024 \n28 ربيع الأول 1446 هـ"
    },
    {
      "num": 0,
      "postTime": "04:38",
      "opTime": "",
      "target": "ثكنة الشوميرا",
      "weapon": "صلية صاروخية",
      "badge": "deep",
      "tags": [
        "ضربة عمق"
      ],
      "fullText": "2\n\nبيان صادر عن المقاومة الإسلامية: \n \nبِسْمِ اللَّـهِ الرحمن الرَّحِيمِ \n﴿أُذِنَ لِلَّذِينَ يُقَاتَلُونَ بِأَنَّهُمْ ظُلِمُوا وَإِنَّ اللَّهَ على نَصْرِهِمْ لَقَدِيرٌ﴾ \nصدق الله العلي العظيم \n \nدعماً لشعبنا الفلسطيني الصامد في قطاع غزة وإسناداً لمقاومته الباسلة ‌‏‌‏‌والشريفة، ودفاعًا عن لبنان ‏وشعبه، استهدف مجاهدو المقاومة ‏الإسلامية عند الساعة (7:15) من صباح يوم الأربعاء 2-10-2024 تجمعاً لِقوات العدو الإسرائيلي في ثكنة الشوميرا بِصلية صاروخية وحققوا فيه إصابةً مباشرة.  \n \n﴿وَمَا النَّصْرُ إِلاَّ مِنْ عِندِ اللّهِ الْعَزِيزِ الْحَكِيم﴾ \nالأربعاء 2-10-2024 \n28 ربيع الأول 1446 هـ"
    },
    {
      "num": 0,
      "postTime": "04:58",
      "opTime": "",
      "target": "الساعة",
      "weapon": "",
      "badge": "",
      "tags": [],
      "fullText": "3\n\nبيان صادر عن المقاومة الإسلامية: \n\nبِسْمِ اللَّـهِ الرحمن الرَّحِيمِ \n﴿أُذِنَ لِلَّذِينَ يُقَاتَلُونَ بِأَنَّهُمْ ظُلِمُوا وَإِنَّ اللَّهَ على نَصْرِهِمْ لَقَدِيرٌ﴾ \nصدق الله العلي العظيم \n\nدعماً لشعبنا الفلسطيني الصامد في قطاع غزة وإسناداً لمقاومته الباسلة ‌‏‌‏‌والشريفة، ودفاعًا عن لبنان ‏وشعبه، استهدف مجاهدو المقاومة ‏الإسلامية عند الساعة (7:20) من صباح يوم الأربعاء 2-10-2024 تجمعاً لِقوات العدو الإسرائيلي في مستعمرة شتولا بِصاروخي بركان وحققوا فيه إصاباتٍ مؤكدة.  \n\n﴿وَمَا النَّصْرُ إِلاَّ مِنْ عِندِ اللّهِ الْعَزِيزِ الْحَكِيم﴾ \nالأربعاء 2-10-2024 \n28 ربيع الأول 1446 هـ"
    },
    {
      "num": 0,
      "postTime": "05:00",
      "opTime": "",
      "target": "مستعمرة مسكفعام",
      "weapon": "",
      "badge": "",
      "tags": [],
      "fullText": "4\n\nبيان صادر عن المقاومة الإسلامية:‏\n\nبِسْمِ اللَّـهِ الرحمن الرَّحِيمِ\n‏﴿أُذِنَ لِلَّذِينَ يُقَاتَلُونَ بِأَنَّهُمْ ظُلِمُوا وَإِنَّ اللَّهَ على نَصْرِهِمْ لَقَدِيرٌ﴾‏\nصدق الله العلي العظيم\n\nدعماً لشعبنا الفلسطيني الصاٍمد في قطاع غزة وإسناداً لمقاومته الباسلة ‌‏‌‏‌والشريفة، ودفاعًا عن لبنان ‌‏وشعبه، استهدف مجاهدو المقاومة ‏الإسلامية عند الساعة 7:15 من صباح يوم الأربعاء 2-10-‌‏2024 قوة مشاة كبيرة في مستعمرة مسكفعام بالأسلحة الصاروخية والمدفعية وحققوا فيها إصابة ‏مباشرة ودقيقة.‏\n\n‏﴿وَمَا النَّصْرُ إِلاَّ مِنْ عِندِ اللّهِ الْعَزِيزِ الْحَكِيم﴾‏\nالأربعاء 2-10-2024‏\n‏28 ربيع الأول  1446 هـ"
    },
    {
      "num": 0,
      "postTime": "05:54",
      "opTime": "",
      "target": "الساعة",
      "weapon": "صلية صاروخية",
      "badge": "",
      "tags": [],
      "fullText": "5\n\nبيان صادر عن المقاومة الإسلامية: \n \nبِسْمِ اللَّـهِ الرحمن الرَّحِيمِ \n﴿أُذِنَ لِلَّذِينَ يُقَاتَلُونَ بِأَنَّهُمْ ظُلِمُوا وَإِنَّ اللَّهَ على نَصْرِهِمْ لَقَدِيرٌ﴾ \nصدق الله العلي العظيم \n \nدعماً لشعبنا الفلسطيني الصامد في قطاع غزة وإسناداً لمقاومته الباسلة ‌‏‌‏‌والشريفة، ودفاعًا عن لبنان ‏وشعبه، استهدف مجاهدو المقاومة ‏الإسلامية عند الساعة (7:30) من صباح يوم الأربعاء 2-10-2024 تجمعاً لِقوات العدو الإسرائيلي ومرابض مدفعيته جنوب كريات شمونة بِصلية صاروخية وحققوا فيها إصاباتٍ مؤكدة.  \n \n﴿وَمَا النَّصْرُ إِلاَّ مِنْ عِندِ اللّهِ الْعَزِيزِ الْحَكِيم﴾ \nالأربعاء 2-10-2024 \n28 ربيع الأول 1446 هـ"
    },
    {
      "num": 0,
      "postTime": "06:43",
      "opTime": "",
      "target": "ثكنة زرعيت",
      "weapon": "صلية صاروخية",
      "badge": "deep",
      "tags": [
        "إصابة مباشرة",
        "ضربة عمق"
      ],
      "fullText": "6\n\nبيان صادر عن المقاومة الإسلامية:‏\n\nبِسْمِ اللَّـهِ الرحمن الرَّحِيمِ\n‏﴿أُذِنَ لِلَّذِينَ يُقَاتَلُونَ بِأَنَّهُمْ ظُلِمُوا وَإِنَّ اللَّهَ على نَصْرِهِمْ لَقَدِيرٌ﴾‏\nصدق الله العلي العظيم\n\nدعماً لشعبنا الفلسطيني الصاٍمد في قطاع غزة وإسناداً لمقاومته الباسلة ‌‏‌‏‌والشريفة، ودفاعًا عن لبنان ‌‏وشعبه، استهدف مجاهدو المقاومة ‏الإسلامية عند الساعة 9:20 من صباح يوم الأربعاء 2-10-‌‏2024 ثكنة زرعيت بصلية صاروخية من الكاتيوشا وحققوا فيها إصابة مباشرة ودقيقة.‏\n\n‏﴿وَمَا النَّصْرُ إِلاَّ مِنْ عِندِ اللّهِ الْعَزِيزِ الْحَكِيم﴾‏\nالأربعاء 2-10-2024‏\n‏28 ربيع الأول  1446 هـ"
    },
    {
      "num": 0,
      "postTime": "08:08",
      "opTime": "",
      "target": "الساعة",
      "weapon": "صلية صاروخية",
      "badge": "",
      "tags": [],
      "fullText": "7\n\nبيان صادر عن المقاومة الإسلامية: \n \nبِسْمِ اللَّـهِ الرحمن الرَّحِيمِ \n﴿أُذِنَ لِلَّذِينَ يُقَاتَلُونَ بِأَنَّهُمْ ظُلِمُوا وَإِنَّ اللَّهَ على نَصْرِهِمْ لَقَدِيرٌ﴾ \nصدق الله العلي العظيم \n \nدعماً لشعبنا الفلسطيني الصامد في قطاع غزة وإسناداً لمقاومته الباسلة ‌‏‌‏‌والشريفة، ودفاعًا عن لبنان ‏وشعبه، استهدف مجاهدو المقاومة ‏الإسلامية عند الساعة (9:30) من صباح يوم الأربعاء 2-10-2024 تجمعاً لِقوات العدو الإسرائيلي في مستعمرة أفيفيم بِصلية صاروخية كبيرة. \n \n﴿وَمَا النَّصْرُ إِلاَّ مِنْ عِندِ اللّهِ الْعَزِيزِ الْحَكِيم﴾ \nالأربعاء 2-10-2024 \n28 ربيع الأول 1446 هـ"
    },
    {
      "num": 0,
      "postTime": "08:13",
      "opTime": "",
      "target": "ثكنة أفيفيم",
      "weapon": "صلية صاروخية",
      "badge": "deep",
      "tags": [
        "ضربة عمق"
      ],
      "fullText": "8\n\nبيان صادر عن المقاومة الإسلامية: \n \nبِسْمِ اللَّـهِ الرحمن الرَّحِيمِ \n﴿أُذِنَ لِلَّذِينَ يُقَاتَلُونَ بِأَنَّهُمْ ظُلِمُوا وَإِنَّ اللَّهَ على نَصْرِهِمْ لَقَدِيرٌ﴾ \nصدق الله العلي العظيم \n \nدعماً لشعبنا الفلسطيني الصامد في قطاع غزة وإسناداً لمقاومته الباسلة ‌‏‌‏‌والشريفة، ودفاعًا عن لبنان ‏وشعبه، استهدف مجاهدو المقاومة ‏الإسلامية عند الساعة (9:30) من صباح يوم الأربعاء 2-10-2024 تجمعاً لِقوات العدو الإسرائيلي في ثكنة أفيفيم بِصلية صاروخية كبيرة. \n \n﴿وَمَا النَّصْرُ إِلاَّ مِنْ عِندِ اللّهِ الْعَزِيزِ الْحَكِيم﴾ \nالأربعاء 2-10-2024 \n28 ربيع الأول 1446 هـ"
    },
    {
      "num": 0,
      "postTime": "08:32",
      "opTime": "",
      "target": "حيفا",
      "weapon": "صلية صاروخية",
      "badge": "",
      "tags": [],
      "fullText": "9\n\nبيان صادر عن المقاومة الإسلامية: \n \nبِسْمِ اللَّـهِ الرحمن الرَّحِيمِ \n﴿أُذِنَ لِلَّذِينَ يُقَاتَلُونَ بِأَنَّهُمْ ظُلِمُوا وَإِنَّ اللَّهَ على نَصْرِهِمْ لَقَدِيرٌ﴾ \nصدق الله العلي العظيم \n \nدعماً لشعبنا الفلسطيني الصامد في قطاع غزة وإسناداً لمقاومته الباسلة ‌‏‌‏‌والشريفة، ودفاعًا عن لبنان ‏وشعبه، ورداً على الاستباحة الهمجية الإسرائيلية للمدن والقرى والمدنيين، قصف مجاهدو المقاومة ‏الإسلامية عند الساعة (10:10) من صباح يوم الأربعاء 2-10-2024 مجموعة من الكريات شمال مدينة حيفا بِصلية صاروخية كبيرة. \n \n﴿وَمَا النَّصْرُ إِلاَّ مِنْ عِندِ اللّهِ الْعَزِيزِ الْحَكِيم﴾ \nالأربعاء 2-10-2024 \n28 ربيع الأول 1446 هـ"
    },
    {
      "num": 0,
      "postTime": "09:02",
      "opTime": "",
      "target": "الساعة",
      "weapon": "صلية صاروخية",
      "badge": "",
      "tags": [],
      "fullText": "10\n\nبيان صادر عن المقاومة الإسلامية: \n \nبِسْمِ اللَّـهِ الرحمن الرَّحِيمِ \n﴿أُذِنَ لِلَّذِينَ يُقَاتَلُونَ بِأَنَّهُمْ ظُلِمُوا وَإِنَّ اللَّهَ على نَصْرِهِمْ لَقَدِيرٌ﴾ \nصدق الله العلي العظيم \n \nدعماً لشعبنا الفلسطيني الصامد في قطاع غزة وإسناداً لمقاومته الباسلة ‌‏‌‏‌والشريفة، ودفاعًا عن لبنان ‏وشعبه، استهدف مجاهدو المقاومة ‏الإسلامية عند الساعة (11:30) من نهار يوم الأربعاء 2-10-2024 تجمعاً لِقوات العدو الإسرائيلي في مستعمرة أدميت بِصلية صاروخية وحققوا فيه إصابةً مباشرة.  \n \n﴿وَمَا النَّصْرُ إِلاَّ مِنْ عِندِ اللّهِ الْعَزِيزِ الْحَكِيم﴾ \nالأربعاء 2-10-2024 \n28 ربيع الأول 1446 هـ"
    },
    {
      "num": 0,
      "postTime": "09:54",
      "opTime": "",
      "target": "مارون الراس من الجهة الشرقية وأوقعوا في صفوفهم إصابات عدة",
      "weapon": "",
      "badge": "",
      "tags": [],
      "fullText": "11\n \nبيان صادر عن المقاومة الإسلامية: \n \nبِسْمِ اللَّـهِ الرحمن الرَّحِيمِ \n﴿أُذِنَ لِلَّذِينَ يُقَاتَلُونَ بِأَنَّهُمْ ظُلِمُوا وَإِنَّ اللَّهَ على نَصْرِهِمْ لَقَدِيرٌ﴾ \nصدق الله العلي العظيم \nدعماً لشعبنا الفلسطيني الصامد في قطاع غزة وإسناداً لمقاومته الباسلة ‌‏‌‏‌والشريفة، ودفاعًا عن لبنان ‏وشعبه، تخوض المقاومة الإسلامية اشتباكات مع جنود العدو الإسرائيلي المتسللة إلى بلدة مارون الراس من الجهة الشرقية وأوقعوا في صفوفهم إصابات عدة وما زالت الاشتباكات مستمرة. \n﴿وَمَا النَّصْرُ إِلاَّ مِنْ عِندِ اللّهِ الْعَزِيزِ الْحَكِيم﴾ \nالأربعاء 2-10-2024 \n28 ربيع الأول 1446 هـ"
    },
    {
      "num": 0,
      "postTime": "11:05",
      "opTime": "",
      "target": "قاعدة عميعاد",
      "weapon": "صلية صاروخية",
      "badge": "deep",
      "tags": [
        "ضربة عمق"
      ],
      "fullText": "12\n\nبيان صادر عن المقاومة الإسلامية: \n \nبِسْمِ اللَّـهِ الرحمن الرَّحِيمِ \n﴿أُذِنَ لِلَّذِينَ يُقَاتَلُونَ بِأَنَّهُمْ ظُلِمُوا وَإِنَّ اللَّهَ على نَصْرِهِمْ لَقَدِيرٌ﴾ \nصدق الله العلي العظيم \n \nدعماً لشعبنا الفلسطيني الصامد في قطاع غزة وإسناداً لمقاومته الباسلة ‌‏‌‏‌والشريفة، ودفاعًا عن لبنان وشعبه، ورداً على الاستباحة الهمجية الإسرائيلية للمدن والقرى والمدنيين، قصف مجاهدو المقاومة الإسلامية عند الساعة (01:00) من ظهر يوم الأربعاء 2-10-2024 قاعدة عميعاد بِصلية صاروخية كبيرة وحققوا فيها إصابةً مباشرة. \n﴿وَمَا النَّصْرُ إِلاَّ مِنْ عِندِ اللّهِ الْعَزِيزِ الْحَكِيم﴾ \nالأربعاء 2-10-2024 \n28 ربيع الأول 1446 هـ"
    },
    {
      "num": 0,
      "postTime": "12:14",
      "opTime": "",
      "target": "",
      "weapon": "",
      "badge": "",
      "tags": [],
      "fullText": "13\n\nبيان صادر عن المقاومة الإسلامية: \n \nبِسْمِ اللَّـهِ الرحمن الرَّحِيمِ \n﴿أُذِنَ لِلَّذِينَ يُقَاتَلُونَ بِأَنَّهُمْ ظُلِمُوا وَإِنَّ اللَّهَ على نَصْرِهِمْ لَقَدِيرٌ﴾ \nصدق الله العلي العظيم \n \nدعماً لشعبنا الفلسطيني الصامد في قطاع غزة وإسناداً لمقاومته الباسلة ‌‏‌‏‌والشريفة، ودفاعًا عن لبنان وشعبه، ورداً على الاستباحة الهمجية الإسرائيلية للمدن والقرى والمدنيين، شن مجاهدو المقاومة الإسلامية عند الساعة (01:00) من ظهر يوم الأربعاء 2-10-2024 هجوماً جوياً بسربٍ من المسيرات الإنقضاضية على مربض المدفعية في نافيه زيف وأصابت أهدافها بِدقة. \n﴿وَمَا النَّصْرُ إِلاَّ مِنْ عِندِ اللّهِ الْعَزِيزِ الْحَكِيم﴾ \nالأربعاء 2-10-2024 \n28 ربيع الأول 1446 هـ"
    },
    {
      "num": 0,
      "postTime": "12:24",
      "opTime": "",
      "target": "",
      "weapon": "",
      "badge": "",
      "tags": [],
      "fullText": "14\n\nبيان صادر عن المقاومة الإسلامية: \n \nبِسْمِ اللَّـهِ الرحمن الرَّحِيمِ \n﴿أُذِنَ لِلَّذِينَ يُقَاتَلُونَ بِأَنَّهُمْ ظُلِمُوا وَإِنَّ اللَّهَ على نَصْرِهِمْ لَقَدِيرٌ﴾ \nصدق الله العلي العظيم \n \nدعماً لشعبنا الفلسطيني الصامد في قطاع غزة وإسناداً لمقاومته الباسلة ‌‏‌‏‌والشريفة، ودفاعًا عن لبنان وشعبه، ورداً على الاستباحة الهمجية الإسرائيلية للمدن والقرى والمدنيين، وبينما كانت قوة للعدو الإسرائيلي تُحاول الإلتفاف على بلدة يارون من جهة الحرش، باغتها مجاهدو المقاومة الإسلامية عند الساعة (02:00) من بعد ظهر يوم الأربعاء 2-10-2024 بِتفجير عبوة خاصة وأوقعوا جميع أفراد القوة بين قتيلٍ وجريح. \n﴿وَمَا النَّصْرُ إِلاَّ مِنْ عِندِ اللّهِ الْعَزِيزِ الْحَكِيم﴾ \nالأربعاء 2-10-2024 \n28 ربيع الأول 1446 هـ"
    },
    {
      "num": 0,
      "postTime": "14:02",
      "opTime": "13:00",
      "target": "",
      "weapon": "",
      "badge": "",
      "tags": [
        "إصابة مباشرة"
      ],
      "fullText": "15\n\nبيان صادر عن المقاومة الإسلامية:‏\n\nبِسْمِ اللَّـهِ الرحمن الرَّحِيمِ\n‏﴿أُذِنَ لِلَّذِينَ يُقَاتَلُونَ بِأَنَّهُمْ ظُلِمُوا وَإِنَّ اللَّهَ على نَصْرِهِمْ لَقَدِيرٌ﴾‏\nصدق الله العلي العظيم\n\nدعماً لشعبنا الفلسطيني الصاٍمد في قطاع غزة وإسناداً لمقاومته الباسلة ‌‏‌‏‌والشريفة، ودفاعًا عن لبنان ‌‏وشعبه، استهدف مجاهدو المقاومة ‏الإسلامية عند الساعة 13:00 ظهر يوم الأربعاء 2-10-2024 ‏تجمعًا لقوات العدو بين العديسة ومسكفعام بصاروخ موجه ضد الأفراد وأصابوه إصابة مباشرة، ‏وأوقعوه بين قتيل وجريح.‏\n\n‏﴿وَمَا النَّصْرُ إِلاَّ مِنْ عِندِ اللّهِ الْعَزِيزِ الْحَكِيم﴾‏\nالأربعاء 2-10-2024‏\n‏28 ربيع الأول  1446 هـ"
    },
    {
      "num": 0,
      "postTime": "14:11",
      "opTime": "",
      "target": "الساعة",
      "weapon": "صلية صاروخية",
      "badge": "",
      "tags": [],
      "fullText": "16\n\nبيان صادر عن المقاومة الإسلامية: \n \nبِسْمِ اللَّـهِ الرحمن الرَّحِيمِ \n﴿أُذِنَ لِلَّذِينَ يُقَاتَلُونَ بِأَنَّهُمْ ظُلِمُوا وَإِنَّ اللَّهَ على نَصْرِهِمْ لَقَدِيرٌ﴾ \nصدق الله العلي العظيم \n \nدعماً لشعبنا الفلسطيني الصامد في قطاع غزة وإسناداً لمقاومته الباسلة ‌‏‌‏‌والشريفة، ودفاعًا عن لبنان وشعبه، ورداً على الاستباحة الهمجية الإسرائيلية للمدن والقرى والمدنيين، استهدف مجاهدو المقاومة الإسلامية عند الساعة (3:20) من بعد ظهر يوم الأربعاء 2-10-2024 تجمعاً لِقوات العدو الإسرائيلي في مستعمرة أبيريم بِصلية صاروخية. \n﴿وَمَا النَّصْرُ إِلاَّ مِنْ عِندِ اللّهِ الْعَزِيزِ الْحَكِيم﴾ \nالأربعاء 2-10-2024 \n28 ربيع الأول 1446 هـ"
    },
    {
      "num": 0,
      "postTime": "14:13",
      "opTime": "16:20",
      "target": "",
      "weapon": "صلية صاروخية",
      "badge": "",
      "tags": [
        "إصابة مباشرة"
      ],
      "fullText": "17\n\nبيان صادر عن المقاومة الإسلامية:‏\n\nبِسْمِ اللَّـهِ الرحمن الرَّحِيمِ\n‏﴿أُذِنَ لِلَّذِينَ يُقَاتَلُونَ بِأَنَّهُمْ ظُلِمُوا وَإِنَّ اللَّهَ على نَصْرِهِمْ لَقَدِيرٌ﴾‏\nصدق الله العلي العظيم\n\nدعماً لشعبنا الفلسطيني الصاٍمد في قطاع غزة وإسناداً لمقاومته الباسلة ‌‏‌‏‌والشريفة، ودفاعًا عن لبنان ‌‏وشعبه، استهدف مجاهدو المقاومة ‏الإسلامية عند الساعة 16:20 من بعد ظهر يوم الأربعاء 2-10-‌‏2024 تجمعًا لقوات العدو بين مسكفعام وكفرجلعادي بصلية صاروخية وأصابوه إصابة مباشرة.‏\n\n‏﴿وَمَا النَّصْرُ إِلاَّ مِنْ عِندِ اللّهِ الْعَزِيزِ الْحَكِيم﴾‏\nالأربعاء 2-10-2024‏\n‏28 ربيع الأول  1446 هـ"
    },
    {
      "num": 0,
      "postTime": "14:56",
      "opTime": "",
      "target": "مارون الراس",
      "weapon": "",
      "badge": "tank",
      "tags": [],
      "fullText": "18\n\nبيان صادر عن المقاومة الإسلامية: \n \nبِسْمِ اللَّـهِ الرحمن الرَّحِيمِ \n﴿أُذِنَ لِلَّذِينَ يُقَاتَلُونَ بِأَنَّهُمْ ظُلِمُوا وَإِنَّ اللَّهَ على نَصْرِهِمْ لَقَدِيرٌ﴾ \nصدق الله العلي العظيم \n \nدعماً لشعبنا الفلسطيني الصامد في قطاع غزة وإسناداً لمقاومته الباسلة ‌‏‌‏‌والشريفة، ودفاعًا عن لبنان وشعبه، ورداً على الاستباحة الهمجية الإسرائيلية للمدن والقرى والمدنيين، قام مجاهدو المقاومة الإسلامية عند الساعة (5:00) من عصر اليوم الأربعاء 2-10-2024 بِتدمير ثلاث دبابات ميركافا بِصواريخ موجهة أثناء تقدمها إلى بلدة مارون الراس. \n﴿وَمَا النَّصْرُ إِلاَّ مِنْ عِندِ اللّهِ الْعَزِيزِ الْحَكِيم﴾ \nالأربعاء 2-10-2024 \n28 ربيع الأول 1446 هـ"
    },
    {
      "num": 0,
      "postTime": "15:10",
      "opTime": "",
      "target": "خراج بلدة كفركلا",
      "weapon": "",
      "badge": "",
      "tags": [],
      "fullText": "19\n\nبيان صادر عن المقاومة الإسلامية:‏\n\nبِسْمِ اللَّـهِ الرحمن الرَّحِيمِ\n‏﴿أُذِنَ لِلَّذِينَ يُقَاتَلُونَ بِأَنَّهُمْ ظُلِمُوا وَإِنَّ اللَّهَ على نَصْرِهِمْ لَقَدِيرٌ﴾‏\nصدق الله العلي العظيم\n\nدعماً لشعبنا الفلسطيني الصاٍمد في قطاع غزة وإسناداً لمقاومته الباسلة ‌‏‌‏‌والشريفة، ودفاعًا عن لبنان ‌‌‏وشعبه، وبعد رصد ومراقبة لقوة مشاة صهيونية تسللت إلى منزل في خراج بلدة كفركلا، فجر فيها ‌‏مجاهدو المقاومة ‏الإسلامية عند الساعة 2:30 من بعد ظهر يوم الأربعاء 2-10-2024 عبوة معدة ‌‏مسبقا قبل أن يمطروها بوابل من الأسلحة الرشاشة والقذائف الصاروخية وأوقعوا أفرادها بين قتيل ‌‏وجريح. ‏\n\n‏﴿وَمَا النَّصْرُ إِلاَّ مِنْ عِندِ اللّهِ الْعَزِيزِ الْحَكِيم﴾‏\nالأربعاء 2-10-2024‏\n‏28 ربيع الأول  1446 هـ"
    },
    {
      "num": 0,
      "postTime": "15:12",
      "opTime": "",
      "target": "بساتين المطلة",
      "weapon": "",
      "badge": "",
      "tags": [],
      "fullText": "20\n\nبيان صادر عن المقاومة الإسلامية:‏\n\nبِسْمِ اللَّـهِ الرحمن الرَّحِيمِ\n‏﴿أُذِنَ لِلَّذِينَ يُقَاتَلُونَ بِأَنَّهُمْ ظُلِمُوا وَإِنَّ اللَّهَ على نَصْرِهِمْ لَقَدِيرٌ﴾‏\nصدق الله العلي العظيم\n\nدعماً لشعبنا الفلسطيني الصاٍمد في قطاع غزة وإسناداً لمقاومته الباسلة ‌‏‌‏‌والشريفة، ودفاعًا عن لبنان ‌‏وشعبه، استهدف مجاهدو المقاومة ‏الإسلامية عند الساعة 3:20 من بعد ظهر يوم الأربعاء 2-10-‌‏2024 تجمعا لقوات العدو في بساتين المطلة بالأسلحة المدفعية والصاروخية وأصابوه إصابة ‏مباشرة.‏\n\n‏﴿وَمَا النَّصْرُ إِلاَّ مِنْ عِندِ اللّهِ الْعَزِيزِ الْحَكِيم﴾‏\nالأربعاء 2-10-2024‏\n‏28 ربيع الأول  1446 هـ"
    },
    {
      "num": 0,
      "postTime": "15:13",
      "opTime": "",
      "target": "",
      "weapon": "",
      "badge": "",
      "tags": [],
      "fullText": "21\n\nبيان صادر عن المقاومة الإسلامية: \n \nبِسْمِ اللَّـهِ الرحمن الرَّحِيمِ \n﴿أُذِنَ لِلَّذِينَ يُقَاتَلُونَ بِأَنَّهُمْ ظُلِمُوا وَإِنَّ اللَّهَ على نَصْرِهِمْ لَقَدِيرٌ﴾ \nصدق الله العلي العظيم \n \nدعماً لشعبنا الفلسطيني الصامد في قطاع غزة وإسناداً لمقاومته الباسلة ‌‏‌‏‌والشريفة، ودفاعًا عن لبنان وشعبه، ورداً على الاستباحة الهمجية الإسرائيلية للمدن والقرى والمدنيين، ولدى محاولة قوة مشاة إسرائيلية معادية التسلل بإتجاه بلدة يارون من جهة مرتفع السلس، فجر مجاهدو المقاومة الإسلامية عند الساعة (5:40) من عصر اليوم الأربعاء 2-10-2024 عبوة ناسفة بالقوة المتقدمة، ما أدى إلى وقوع أفرادها بين قتيلٍ وجريح. \n﴿وَمَا النَّصْرُ إِلاَّ مِنْ عِندِ اللّهِ الْعَزِيزِ الْحَكِيم﴾ \nالأربعاء 2-10-2024 \n28 ربيع الأول 1446 هـ"
    },
    {
      "num": 0,
      "postTime": "15:16",
      "opTime": "",
      "target": "‏مستعمرة بيت هلل مما أجبرها على المغادرة على الفور",
      "weapon": "",
      "badge": "",
      "tags": [],
      "fullText": "22\n\nبيان صادر عن المقاومة الإسلامية:‏\n\nبِسْمِ اللَّـهِ الرحمن الرَّحِيمِ\n‏﴿أُذِنَ لِلَّذِينَ يُقَاتَلُونَ بِأَنَّهُمْ ظُلِمُوا وَإِنَّ اللَّهَ على نَصْرِهِمْ لَقَدِيرٌ﴾‏\nصدق الله العلي العظيم\n\nدعماً لشعبنا الفلسطيني الصاٍمد في قطاع غزة وإسناداً لمقاومته الباسلة ‌‏‌‏‌والشريفة، ودفاعًا عن لبنان ‌‏وشعبه، وعند الساعة الخامسة صباحا وفي إطار المواجهة المباشرة مع قوات العدو، أطلق مجاهدو ‏المقاومة الإسلامية في وحدات الدفاع الجوي صاروخ أرض-جو على مروحية معادية في أجواء ‏مستعمرة بيت هلل مما أجبرها على المغادرة على الفور، ومنذ ذلك الحين لم تظهر أي مروحية في ‏الأجواء على امتداد الحدود اللبنانية مع فلسطين المحتلة. ‏\n\n‏﴿وَمَا النَّصْرُ إِلاَّ مِنْ عِندِ اللّهِ الْعَزِيزِ الْحَكِيم﴾‏\nالأربعاء 2-10-2024‏\n‏28 ربيع الأول  1446 هـ"
    },
    {
      "num": 0,
      "postTime": "15:56",
      "opTime": "",
      "target": "مستعمرة يعرا",
      "weapon": "صلية صاروخية",
      "badge": "",
      "tags": [],
      "fullText": "23\n\nبيان صادر عن المقاومة الإسلامية:‏\n\nبِسْمِ اللَّـهِ الرحمن الرَّحِيمِ\n‏﴿أُذِنَ لِلَّذِينَ يُقَاتَلُونَ بِأَنَّهُمْ ظُلِمُوا وَإِنَّ اللَّهَ على نَصْرِهِمْ لَقَدِيرٌ﴾‏\nصدق الله العلي العظيم\n\nدعماً لشعبنا الفلسطيني الصاٍمد في قطاع غزة وإسناداً لمقاومته الباسلة ‌‏‌‏‌والشريفة، ودفاعًا عن لبنان ‌‏وشعبه، استهدف مجاهدو المقاومة الإسلامية عند الساعة 5:50 من بعد ظهر يوم الأربعاء 2-10-‌‏2024، تحشّدا لقوات العدو في مستعمرة يعرا بصلية صاروخية كبيرة.‏\n\n‏﴿وَمَا النَّصْرُ إِلاَّ مِنْ عِندِ اللّهِ الْعَزِيزِ الْحَكِيم﴾‏\nالأربعاء 2-10-2024‏\n‏28 ربيع الأول  1446 هـ"
    },
    {
      "num": 0,
      "postTime": "16:00",
      "opTime": "",
      "target": "مارون الراس يوم ‏",
      "weapon": "",
      "badge": "",
      "tags": [],
      "fullText": "24\n\nبيان صادر عن المقاومة الإسلامية:‏\n\nبِسْمِ اللَّـهِ الرحمن الرَّحِيمِ\n‏﴿أُذِنَ لِلَّذِينَ يُقَاتَلُونَ بِأَنَّهُمْ ظُلِمُوا وَإِنَّ اللَّهَ على نَصْرِهِمْ لَقَدِيرٌ﴾‏\nصدق الله العلي العظيم\n\nدعماً لشعبنا الفلسطيني الصاٍمد في قطاع غزة وإسناداً لمقاومته الباسلة ‌‏‌‏‌والشريفة، ودفاعًا عن لبنان ‌‏وشعبه، ولدى تحرّك قوة إسرائيلية معادية شرق بلدة مارون الراس عند الساعة 6:20 من مساء يوم ‏الأربعاء 2-10-2024، أمطرها مجاهدو المقاومة الإسلامية بوابل من الأسلحة الرشاشة والقذائف ‏الصاروخية وما زالت الاشتباكات مستمرة.‏\n\n‏﴿وَمَا النَّصْرُ إِلاَّ مِنْ عِندِ اللّهِ الْعَزِيزِ الْحَكِيم﴾‏\nالأربعاء 2-10-2024‏\n‏28 ربيع الأول  1446 هـ"
    },
    {
      "num": 0,
      "postTime": "16:40",
      "opTime": "",
      "target": "",
      "weapon": "",
      "badge": "",
      "tags": [
        "إصابة مباشرة"
      ],
      "fullText": "25\n\nبيان صادر عن المقاومة الإسلامية:‏\n\nبِسْمِ اللَّـهِ الرحمن الرَّحِيمِ\n‏﴿أُذِنَ لِلَّذِينَ يُقَاتَلُونَ بِأَنَّهُمْ ظُلِمُوا وَإِنَّ اللَّهَ على نَصْرِهِمْ لَقَدِيرٌ﴾‏\nصدق الله العلي العظيم\n\nدعماً لشعبنا الفلسطيني الصاٍمد في قطاع غزة وإسناداً لمقاومته الباسلة ‌‏‌‏‌والشريفة، ودفاعًا عن لبنان ‌‏وشعبه، استهدف مجاهدو المقاومة ‏الإسلامية عند الساعة 6:50 من مساء يوم الأربعاء 2-10-‌‏2024 قوات العدو الإسرائيلي أثناء تحركهم داخل مستعمرة شتولا بالأسلحة الصاروخية وأصابوها ‏إصابة مباشرة.‏\n\n‏﴿وَمَا النَّصْرُ إِلاَّ مِنْ عِندِ اللّهِ الْعَزِيزِ الْحَكِيم﴾‏\nالأربعاء 2-10-2024‏\n‏28 ربيع الأول  1446 هـ"
    },
    {
      "num": 0,
      "postTime": "17:30",
      "opTime": "",
      "target": "عفدون شرق نهاريا",
      "weapon": "صلية صاروخية",
      "badge": "",
      "tags": [],
      "fullText": "26\n\nبيان صادر عن المقاومة الإسلامية: \n \nبِسْمِ اللَّـهِ الرحمن الرَّحِيمِ \n﴿أُذِنَ لِلَّذِينَ يُقَاتَلُونَ بِأَنَّهُمْ ظُلِمُوا وَإِنَّ اللَّهَ على نَصْرِهِمْ لَقَدِيرٌ﴾ \nصدق الله العلي العظيم \n \nدعماً لشعبنا الفلسطيني الصامد في قطاع غزة وإسناداً لمقاومته الباسلة ‌‏‌‏‌والشريفة، ودفاعًا عن لبنان ‏وشعبه، استهدف مجاهدو المقاومة ‏الإسلامية عند الساعة (19:30) من مساء يوم الأربعاء 2-10-2024 تجمعاً لِقوات العدو الإسرائيلي في منطقة عفدون شرق نهاريا بِصلية صاروخية. \n \n﴿وَمَا النَّصْرُ إِلاَّ مِنْ عِندِ اللّهِ الْعَزِيزِ الْحَكِيم﴾ \nالأربعاء 2-10-2024 \n28 ربيع الأول 1446 هـ"
    },
    {
      "num": 0,
      "postTime": "17:57",
      "opTime": "",
      "target": "الساعة",
      "weapon": "صلية صاروخية",
      "badge": "",
      "tags": [],
      "fullText": "27\n\nبيان صادر عن المقاومة الإسلامية: \n \nبِسْمِ اللَّـهِ الرحمن الرَّحِيمِ \n﴿أُذِنَ لِلَّذِينَ يُقَاتَلُونَ بِأَنَّهُمْ ظُلِمُوا وَإِنَّ اللَّهَ على نَصْرِهِمْ لَقَدِيرٌ﴾ \nصدق الله العلي العظيم \n \nدعماً لشعبنا الفلسطيني الصامد في قطاع غزة وإسناداً لمقاومته الباسلة ‌‏‌‏‌والشريفة، ودفاعًا عن لبنان ‏وشعبه، استهدف مجاهدو المقاومة ‏الإسلامية عند الساعة (8:00) من مساء يوم الأربعاء 2-10-2024 تجمعاً لِقوات العدو الإسرائيلي في مستعمرة روش بينا بِصلية صاروخية كبيرة. \n \n﴿وَمَا النَّصْرُ إِلاَّ مِنْ عِندِ اللّهِ الْعَزِيزِ الْحَكِيم﴾ \nالأربعاء 2-10-2024 \n28 ربيع الأول 1446 هـ"
    },
    {
      "num": 0,
      "postTime": "22:54",
      "opTime": "",
      "target": "موقع حانيتا",
      "weapon": "",
      "badge": "",
      "tags": [],
      "fullText": "1\n\nبيان صادر عن المقاومة الإسلامية: \n \nبِسْمِ اللَّـهِ الرحمن الرَّحِيمِ \n﴿أُذِنَ لِلَّذِينَ يُقَاتَلُونَ بِأَنَّهُمْ ظُلِمُوا وَإِنَّ اللَّهَ على نَصْرِهِمْ لَقَدِيرٌ﴾ \nصدق الله العلي العظيم \n \nدعماً لشعبنا الفلسطيني الصامد في قطاع غزة وإسناداً لمقاومته الباسلة ‌‏‌‏‌والشريفة، ودفاعًا عن لبنان ‏وشعبه، استهدف مجاهدو المقاومة ‏الإسلامية عند الساعة (1:15) من فجر يوم الخميس 3-10-2024 تجمعاً لِقوات العدو الإسرائيلي في موقع حانيتا بقذائف المدفعية وحققوا فيه إصابةً دقيقة.  \n \n﴿وَمَا النَّصْرُ إِلاَّ مِنْ عِندِ اللّهِ الْعَزِيزِ الْحَكِيم﴾ \nالخميس 3-10-2024 \n29 ربيع الأول 1446 هـ"
    },
    {
      "num": 0,
      "postTime": "23:28",
      "opTime": "",
      "target": "الساعة",
      "weapon": "صلية صاروخية",
      "badge": "",
      "tags": [],
      "fullText": "2\n\nبيان صادر عن المقاومة الإسلامية: \n \nبِسْمِ اللَّـهِ الرحمن الرَّحِيمِ \n﴿أُذِنَ لِلَّذِينَ يُقَاتَلُونَ بِأَنَّهُمْ ظُلِمُوا وَإِنَّ اللَّهَ على نَصْرِهِمْ لَقَدِيرٌ﴾ \nصدق الله العلي العظيم \n \nدعماً لشعبنا الفلسطيني الصامد في قطاع غزة وإسناداً لمقاومته الباسلة ‌‏‌‏‌والشريفة، ودفاعًا عن لبنان ‏وشعبه، استهدف مجاهدو المقاومة ‏الإسلامية عند الساعة (2:00) من فجر يوم الخميس 3-10-2024 تحركات لِقوات العدو الإسرائيلي في مستعمرة مسكاف عام بِصلية صاروخية وحققوا فيها إصابةً مباشرة.  \n \n﴿وَمَا النَّصْرُ إِلاَّ مِنْ عِندِ اللّهِ الْعَزِيزِ الْحَكِيم﴾ \nالخميس 3-10-2024 \n29 ربيع الأول 1446 هـ"
    }
  ],
  "sirens": [
    {
      "time": "03:08",
      "location": "في مسكاف عام بأصبع الجليل.",
      "fullText": "#إعلام_العدو \n\nصفارات الإنذار تدوي في مسكاف عام بأصبع الجليل.\n\n#الإعلام_الحربي"
    },
    {
      "time": "03:29",
      "location": "في أفيفيم بالجليل الغربي.",
      "fullText": "#إعلام_العدو \n\nصفارات الإنذار تدوي في أفيفيم بالجليل الغربي.\n\n#الإعلام_الحربي"
    },
    {
      "time": "03:41",
      "location": "في كريات شمونة ومحيطها بإصبع الجليل.",
      "fullText": "#إعلام_العدو \n\nصفارات الإنذار تدوي في كريات شمونة ومحيطها بإصبع الجليل.\n\n#الإعلام_الحربي"
    },
    {
      "time": "04:08",
      "location": "في المطلة بإصبع الجليل.",
      "fullText": "#إعلام_العدو \n\nصفارات الإنذار تدوي في المطلة بإصبع الجليل.\n\n#الإعلام_الحربي"
    },
    {
      "time": "04:11",
      "location": "في زرعيت والشوميرا بالجليل الغربي.",
      "fullText": "#إعلام_العدو \n\nصفارات الإنذار تدوي في زرعيت والشوميرا بالجليل الغربي.\n\n#الإعلام_الحربي"
    },
    {
      "time": "04:12",
      "location": "في إفن مناحم بالجليل الغربي.",
      "fullText": "#إعلام_العدو \n\nصفارات الإنذار تدوي في إفن مناحم بالجليل الغربي.\n\n#الإعلام_الحربي"
    },
    {
      "time": "04:21",
      "location": "في شتولا بالجليل الغربي.",
      "fullText": "#إعلام_العدو \n\nصفارات الإنذار تدوي في شتولا بالجليل الغربي.\n\n#الإعلام_الحربي"
    },
    {
      "time": "04:26",
      "location": "في المطلة بإصبع الجليل.",
      "fullText": "#إعلام_العدو \n\nصفارات الإنذار تدوي في المطلة بإصبع الجليل.\n\n#الإعلام_الحربي"
    },
    {
      "time": "04:39",
      "location": "في يرؤون بالجليل الغربي.",
      "fullText": "#إعلام_العدو \n\nصفارات الإنذار تدوي في يرؤون بالجليل الغربي.\n\n#الإعلام_الحربي"
    },
    {
      "time": "05:01",
      "location": "في كريات شمونه ومحيطها.",
      "fullText": "#إعلام_العدو \n\nصفارات الإنذار تدوي في كريات شمونه ومحيطها.\n\n#الإعلام_الحربي"
    },
    {
      "time": "05:25",
      "location": "في افن مناحم، زرعيت، شوميراه، وشتولا بالجليل الغربي.",
      "fullText": "#إعلام_العدو \n\nصفارات الإنذار تدوي في افن مناحم، زرعيت، شوميراه، وشتولا بالجليل الغربي.\n\n#الإعلام_الحربي"
    },
    {
      "time": "05:33",
      "location": "في مسكفعام في إصبع الجليل.",
      "fullText": "#إعلام_العدو \n\nصفارات الإنذار تدوي في مسكفعام في إصبع الجليل.\n\n#الإعلام_الحربي"
    },
    {
      "time": "05:36",
      "location": "في كريات شمونه ومحيطها من جديد.",
      "fullText": "#إعلام_العدو\n\nصفارات الإنذار تدوي في كريات شمونه ومحيطها من جديد.\n\n#الإعلام_الحربي"
    },
    {
      "time": "05:55",
      "location": "في شامير في سهل الحولة.",
      "fullText": "#إعلام_العدو \n\nصفارات الإنذار تدوي في شامير في سهل الحولة.\n\n#الإعلام_الحربي"
    },
    {
      "time": "06:15",
      "location": "في زرعيت وعرب العرامشة بالجليل الغربي.",
      "fullText": "#إعلام_العدو \n\nصفارات الإنذار تدوي في زرعيت وعرب العرامشة بالجليل الغربي.\n\n#الإعلام_الحربي"
    },
    {
      "time": "06:18",
      "location": "في المطلة.",
      "fullText": "#إعلام_العدو \n\nصفارات الإنذار تدوي في المطلة.\n\n#الإعلام_الحربي"
    },
    {
      "time": "06:28",
      "location": "في يرؤون، أفيفيم، علما، والريحانية بالجليل الغربي.",
      "fullText": "#إعلام_العدو \n\nصفارات الإنذار تدوي في يرؤون، أفيفيم، علما، والريحانية بالجليل الغربي.\n\n#الإعلام_الحربي"
    },
    {
      "time": "06:51",
      "location": "في مسكفعام في إصبع الجليل.",
      "fullText": "#إعلام_العدو \n\nصفارات الإنذار تدوي في مسكفعام في إصبع الجليل.\n\n#الإعلام_الحربي"
    },
    {
      "time": "06:53",
      "location": "في كريات بياليك وكريات موتسكين شمال حيفا.",
      "fullText": "#إعلام_العدو \n\nصفارات الإنذار تدوي في كريات بياليك وكريات موتسكين شمال حيفا.\n\n#الإعلام_الحربي"
    },
    {
      "time": "06:55",
      "location": "في عفدون، يعرا، إدميت، وعرب العرامشة بالجليل الغربي.",
      "fullText": "#إعلام_العدو \n\nصفارات الإنذار تدوي في عفدون، يعرا، إدميت، وعرب العرامشة بالجليل الغربي.\n\n#الإعلام_الحربي"
    },
    {
      "time": "08:28",
      "location": "في عفدون، حانيتا، يعرا، وكابري بالجليل الغربي.",
      "fullText": "#إعلام_العدو \n\nصفارات الإنذار تدوي في عفدون، حانيتا، يعرا، وكابري بالجليل الغربي.\n\n#الإعلام_الحربي"
    },
    {
      "time": "08:34",
      "location": "في يرؤون بالجليل الغربي.",
      "fullText": "#إعلام_العدو \n\nصفارات الإنذار تدوي في يرؤون بالجليل الغربي.\n\n#الإعلام_الحربي"
    },
    {
      "time": "09:10",
      "location": "في عدد من مستوطنات الجليل الغربي خشية تسلل طائرات مسيّرة.",
      "fullText": "#إعلام_العدو \n\nصفارات الإنذار تدوي في عدد من مستوطنات الجليل الغربي خشية تسلل طائرات مسيّرة.\n\n#الإعلام_الحربي"
    },
    {
      "time": "10:02",
      "location": "في صفد ومحيطها.",
      "fullText": "#إعلام_العدو \n\nصفارات الإنذار تدوي في صفد ومحيطها.\n\n#الإعلام_الحربي"
    },
    {
      "time": "10:02",
      "location": "جنوب صفد.",
      "fullText": "#إعلام_العدو \n\nصفارات الإنذار تدوي جنوب صفد.\n\n#الإعلام_الحربي"
    },
    {
      "time": "10:03",
      "location": "في المناطق الواقعة بين بحيرة طبريا وصفد.",
      "fullText": "#إعلام_العدو \n\nصفارات الإنذار تدوي في المناطق الواقعة بين بحيرة طبريا وصفد.\n\n#الإعلام_الحربي"
    },
    {
      "time": "10:07",
      "location": "في نيفيه زيف، عفدون، ومانوت بالجليل الغربي خشية تسلل طائرات مسيّرة.",
      "fullText": "#إعلام_العدو \n\nصفارات الإنذار تدوي في نيفيه زيف، عفدون، ومانوت بالجليل الغربي خشية تسلل طائرات مسيّرة.\n\n#الإعلام_الحربي"
    },
    {
      "time": "10:10",
      "location": "في جعتون، يخيام، وكليل بالجليل الغربي خشية تسلل طائرات مسيّرة.",
      "fullText": "#إعلام_العدو \n\nصفارات الإنذار تدوي في جعتون، يخيام، وكليل بالجليل الغربي خشية تسلل طائرات مسيّرة.\n\n#الإعلام_الحربي"
    },
    {
      "time": "10:12",
      "location": "في يرؤون بالجليل الغربي.",
      "fullText": "#إعلام_العدو \n\nصفارات الإنذار تدوي في يرؤون بالجليل الغربي.\n\n#الإعلام_الحربي"
    },
    {
      "time": "11:45",
      "location": "في مسكفعام في إصبع الجليل.",
      "fullText": "#إعلام_العدو \n\nصفارات الإنذار تدوي في مسكفعام في إصبع الجليل.\n\n#الإعلام_الحربي"
    },
    {
      "time": "11:50",
      "location": "في كريات شمونه ومحيطها.",
      "fullText": "#إعلام_العدو \n\nصفارات الإنذار تدوي في كريات شمونه ومحيطها.\n\n#الإعلام_الحربي"
    },
    {
      "time": "11:52",
      "location": "في مسكفعام في إصبع الجليل.",
      "fullText": "#إعلام_العدو\n\nصفارات الإنذار تدوي في مسكفعام في إصبع الجليل.\n\n#الإعلام_الحربي"
    },
    {
      "time": "12:36",
      "location": "في افن مناحم في الجليل الغربي.",
      "fullText": "#إعلام_العدو \n\nصفارات الإنذار تدوي في افن مناحم في الجليل الغربي.\n\n#الإعلام_الحربي"
    },
    {
      "time": "13:19",
      "location": "في مسكفعام في إصبع الجليل.",
      "fullText": "#إعلام_العدو \n\nصفارات الإنذار تدوي في مسكفعام في إصبع الجليل.\n\n#الإعلام_الحربي"
    },
    {
      "time": "14:21",
      "location": "في المطلة في إصبع الجليل.",
      "fullText": "#إعلام_العدو \n\nصفارات الإنذار تدوي في المطلة في إصبع الجليل.\n\n#الإعلام_الحربي"
    },
    {
      "time": "14:34",
      "location": "في مسكفعام في إصبع الجليل.",
      "fullText": "#إعلام_العدو \n\nصفارات الإنذار تدوي في مسكفعام في إصبع الجليل.\n\n#الإعلام_الحربي"
    },
    {
      "time": "14:49",
      "location": "في عدد من مستوطنات الجليل الغربي.",
      "fullText": "#إعلام_العدو\n\nصفارات الإنذار تدوي في عدد من مستوطنات الجليل الغربي.\n\n#الإعلام_الحربي"
    },
    {
      "time": "15:37",
      "location": "في أفيفيم بالجليل الغربي.",
      "fullText": "#إعلام_العدو \n\nصفارات الإنذار تدوي في أفيفيم بالجليل الغربي.\n\n#الإعلام_الحربي"
    },
    {
      "time": "15:39",
      "location": "في أفيفيم ويرؤون من جديد بالجليل الغربي.",
      "fullText": "#إعلام_العدو \n\nصفارات الإنذار تدوي في أفيفيم ويرؤون من جديد بالجليل الغربي.\n\n#الإعلام_الحربي"
    },
    {
      "time": "16:26",
      "location": "في نهاريا ومحيطها.",
      "fullText": "#إعلام_العدو \n\nصفارات الإنذار تدوي في نهاريا ومحيطها.\n\n#الإعلام_الحربي"
    },
    {
      "time": "17:01",
      "location": "في المناطق الواقعة شرق صفد.",
      "fullText": "#إعلام_العدو \n\nصفارات الإنذار تدوي في المناطق الواقعة شرق صفد.\n\n#الإعلام_الحربي"
    },
    {
      "time": "19:14",
      "location": "في صفد ومحيطها.",
      "fullText": "#إعلام_العدو\n\nصفارات الإنذار تدوي في صفد ومحيطها.\n\n#الإعلام_الحربي"
    },
    {
      "time": "20:08",
      "location": "في أفيفيم بالجليل الغربي.",
      "fullText": "#إعلام_العدو \n\nصفارات الإنذار تدوي في أفيفيم بالجليل الغربي.\n\n#الإعلام_الحربي"
    },
    {
      "time": "21:48",
      "location": "في حانيتا بالجليل الغربي.",
      "fullText": "#إعلام_العدو \n\nصفارات الإنذار تدوي في حانيتا بالجليل الغربي.\n\n#الإعلام_الحربي"
    },
    {
      "time": "23:54",
      "location": "في بات يام جنوب تل أبيب خشية تسلل طائرات مسيّرة.",
      "fullText": "#إعلام_العدو \n\nصفارات الإنذار تدوي في بات يام جنوب تل أبيب خشية تسلل طائرات مسيّرة.\n\n#الإعلام_الحربي"
    }
  ],
  "sirenPoints": [
    {
      "lat": 33.05,
      "lng": 35.15,
      "loc": "الجليل الغربي",
      "times": [
        "03:29",
        "04:11",
        "04:12",
        "04:21",
        "04:39",
        "05:25",
        "06:15",
        "06:28",
        "06:55",
        "08:28",
        "08:34",
        "09:10",
        "10:07",
        "10:10",
        "10:12",
        "12:36",
        "14:49",
        "15:37",
        "15:39",
        "20:08",
        "21:48"
      ],
      "count": 21
    },
    {
      "lat": 33.2,
      "lng": 35.57,
      "loc": "إصبع الجليل",
      "times": [
        "04:08",
        "04:26",
        "05:33",
        "06:51",
        "11:45",
        "11:52",
        "13:19",
        "14:21",
        "14:34"
      ],
      "count": 9
    },
    {
      "lat": 32.9646,
      "lng": 35.4967,
      "loc": "صفد",
      "times": [
        "10:02",
        "10:02",
        "10:03",
        "17:01",
        "19:14"
      ],
      "count": 5
    },
    {
      "lat": 33.2081,
      "lng": 35.5731,
      "loc": "كريات شمونه",
      "times": [
        "05:01",
        "05:36",
        "11:50"
      ],
      "count": 3
    },
    {
      "lat": 33.206,
      "lng": 35.575,
      "loc": "مسكاف عام",
      "times": [
        "03:08"
      ],
      "count": 1
    },
    {
      "lat": 33.2081,
      "lng": 35.5731,
      "loc": "كريات شمونة",
      "times": [
        "03:41"
      ],
      "count": 1
    },
    {
      "lat": 33.28,
      "lng": 35.57,
      "loc": "المطلة",
      "times": [
        "06:18"
      ],
      "count": 1
    },
    {
      "lat": 32.794,
      "lng": 34.9896,
      "loc": "حيفا",
      "times": [
        "06:53"
      ],
      "count": 1
    },
    {
      "lat": 33.0042,
      "lng": 35.0968,
      "loc": "نهاريا",
      "times": [
        "16:26"
      ],
      "count": 1
    },
    {
      "lat": 32.0853,
      "lng": 34.7818,
      "loc": "تل أبيب",
      "times": [
        "23:54"
      ],
      "count": 1
    }
  ],
  "enemy": [
    {
      "time": "04:09",
      "summary": "وسائل إعلام إسرائيلية: تم رصد صاروخ أطلق من لبنان وسقط في منطقة تل أبيب دون تفعيل صافرات الإنذار.",
      "fullText": "#إعلام_العدو \n\nوسائل إعلام إسرائيلية: تم رصد صاروخ أطلق من لبنان وسقط في منطقة تل أبيب دون تفعيل صافرات الإنذار.\n\n#الإعلام_الحربي"
    },
    {
      "time": "04:18",
      "summary": "وسائل إعلام إسرائيلية: حدث أمني عند الحدود الشمالية مع لبنان.",
      "fullText": "#إعلام_العدو\n\nوسائل إعلام إسرائيلية: حدث أمني عند الحدود الشمالية مع لبنان.\n\n#الإعلام_الحربي"
    },
    {
      "time": "04:24",
      "summary": "وسائل إعلام إسرائيلية: الوحدة 669 في الجيش الإسرائيلي عملت على إخلاء الجرحى عند الحدود الشمالية مع لبنان.",
      "fullText": "#إعلام_العدو\n\nوسائل إعلام إسرائيلية: الوحدة 669 في الجيش الإسرائيلي عملت على إخلاء الجرحى عند الحدود الشمالية مع لبنان.\n\n#الإعلام_الحربي"
    },
    {
      "time": "04:42",
      "summary": "وسائل إعلام إسرائيلية: هبوط مروحية عسكرية إسرائيلية في مستشفى رمبام في حيفا.",
      "fullText": "#إعلام_العدو \n\nوسائل إعلام إسرائيلية: هبوط مروحية عسكرية إسرائيلية في مستشفى رمبام في حيفا.\n\n#الإعلام_الحربي"
    },
    {
      "time": "05:04",
      "summary": "وسائل إعلام إسرائيلية: حزب الله يقصف المنطقة الحدودية في الشمال بقوة.",
      "fullText": "#إعلام_العدو \n\nوسائل إعلام إسرائيلية: حزب الله يقصف المنطقة الحدودية في الشمال بقوة.\n\n#الإعلام_الحربي"
    },
    {
      "time": "05:18",
      "summary": "وسائل إعلام إسرائيلية: مروحيات عسكرية إسرائيلية هبطت في مستشفيات رمبام في حيفا وزيف في صفد وبيلنسون في الوسط.",
      "fullText": "#إعلام_العدو \n\nوسائل إعلام إسرائيلية: مروحيات عسكرية إسرائيلية هبطت في مستشفيات رمبام في حيفا وزيف في صفد وبيلنسون في الوسط.\n\n#الإعلام_الحربي"
    },
    {
      "time": "05:33",
      "summary": "وسائل إعلام إسرائيلية: الطواقم الطبية كانت تحاول إنعاش قلب جندي إسرائيلي بعدما أُصيب بجروح بليغة عند الحدود مع لبنان لكن المحاولة باءت بالفشل.",
      "fullText": "#إعلام_العدو \n\nوسائل إعلام إسرائيلية: الطواقم الطبية كانت تحاول إنعاش قلب جندي إسرائيلي بعدما أُصيب بجروح بليغة عند الحدود مع لبنان لكن المحاولة باءت بالفشل.\n\n#الإعلام_الحربي"
    },
    {
      "time": "06:11",
      "summary": "قناة 12 العبرية: عدد من المباني تضررت جراء سقوط صواريخ بشكل مباشر في المطلة.",
      "fullText": "#إعلام_العدو \n\nقناة 12 العبرية: عدد من المباني تضررت جراء سقوط صواريخ بشكل مباشر في المطلة.\n\n#الإعلام_الحربي"
    },
    {
      "time": "06:46",
      "summary": "وسائل إعلام إسرائيلية: وقوع 20 جنديًا إسرائيليًا بين قتيل وجريح جراء الحدث الأمني عند الحدود مع لبنان، وكانت عملية إنقاذهم صعبة جداً بسبب القصف المدفعي الكثيف الذي نفذه حزب الله.",
      "fullText": "#إعلام_العدو \n\nوسائل إعلام إسرائيلية: وقوع 20 جنديًا إسرائيليًا بين قتيل وجريح جراء الحدث الأمني عند الحدود مع لبنان، وكانت عملية إنقاذهم صعبة جداً بسبب القصف المدفعي الكثيف الذي نفذه حزب الله.\n\n#الإعلام_الحربي"
    },
    {
      "time": "06:49",
      "summary": "إذاعة جيش العدو الإسرائيلي: الجيش الإسرائيلي يدعو إلى عدم نشر أسماء الأماكن التي تسقط فيها الصواريخ.",
      "fullText": "#إعلام_العدو \n\nإذاعة جيش العدو الإسرائيلي: الجيش الإسرائيلي يدعو إلى عدم نشر أسماء الأماكن التي تسقط فيها الصواريخ.\n\n#الإعلام_الحربي"
    },
    {
      "time": "08:56",
      "summary": "وسائل إعلام إسرائيلية: الحدث الذي وقع صباح اليوم عند الحدود الشمالية صعب للغاية.",
      "fullText": "#إعلام_العدو \n\nوسائل إعلام إسرائيلية: الحدث الذي وقع صباح اليوم عند الحدود الشمالية صعب للغاية.\n\n#الإعلام_الحربي"
    },
    {
      "time": "10:26",
      "summary": "وسائل إعلام إسرائيلية: قتيل على الأقل من وحدة \"ايغوز\" جراء اشتباكات مع حزب الله عند الحدود الشمالية.",
      "fullText": "#إعلام_العدو \n\nوسائل إعلام إسرائيلية: قتيل على الأقل من وحدة \"ايغوز\" جراء اشتباكات مع حزب الله عند الحدود الشمالية.\n\n#الإعلام_الحربي"
    },
    {
      "time": "10:44",
      "summary": "وسائل إعلام إسرائيلية: مشاهد لإخلاء الجيش الإسرائيلي لقتلى وجرحى وقعوا خلال الاشتباكات مع حزب الله.",
      "fullText": "#إعلام_العدو \n\nوسائل إعلام إسرائيلية: مشاهد لإخلاء الجيش الإسرائيلي لقتلى وجرحى وقعوا خلال الاشتباكات مع حزب الله.\n\n#الإعلام_الحربي"
    },
    {
      "time": "10:49",
      "summary": "المتحدث باسم جيش العدو الإسرائيلي: رصد إطلاق 40 صاروخًا ومسيّرة تجاه الجليل الأعلى ورصد انفجارات في المنطقة.",
      "fullText": "#إعلام_العدو \n\nالمتحدث باسم جيش العدو الإسرائيلي: رصد إطلاق 40 صاروخًا ومسيّرة تجاه الجليل الأعلى ورصد انفجارات في المنطقة.\n\n#الإعلام_الحربي"
    },
    {
      "time": "11:17",
      "summary": "إذاعة جيش العدو الإسرائيلي: الجيش الإسرائيلي يعترف، لقد أصابت الصواريخ الإيرانية قواعد الجيش الإسرائيلي المستهدفة.",
      "fullText": "#إعلام_العدو \n\nإذاعة جيش العدو الإسرائيلي: الجيش الإسرائيلي يعترف، لقد أصابت الصواريخ الإيرانية قواعد الجيش الإسرائيلي المستهدفة.\n\n#الإعلام_الحربي"
    },
    {
      "time": "11:29",
      "summary": "وسائل إعلام إسرائيلية: الصواريخ الإيرانية دمرت مبان ومشاغل صيانة للطائرات الحربية في القواعد الجوية الإسرائيلية.",
      "fullText": "#إعلام_العدو \n\nوسائل إعلام إسرائيلية: الصواريخ الإيرانية دمرت مبان ومشاغل صيانة للطائرات الحربية في القواعد الجوية الإسرائيلية.\n\n#الإعلام_الحربي"
    },
    {
      "time": "11:47",
      "summary": "المتحدث باسم جيش العدو الإسرائيلي: مقتل قائد مجموعة برتبة نقيب من وحدة ايغوز خلال المواجهات عند الحدود مع لبنان.",
      "fullText": "#إعلام_العدو \n\nالمتحدث باسم جيش العدو الإسرائيلي: مقتل قائد مجموعة برتبة نقيب من وحدة ايغوز خلال المواجهات عند الحدود مع لبنان.\n\n#الإعلام_الحربي"
    },
    {
      "time": "11:56",
      "summary": "إذاعة جيش العدو الإسرائيلي: مواجهة حصلت داخل مبنى صباح اليوم عندما تسللت مجموعة من وحدة إيغوز إلى داخله حينها فتح حزب الله النار وأطلق الصواريخ تجاه القوة، وحتى خلال عملية سحب الجرحى واصل حزب الله إطل",
      "fullText": "#إعلام_العدو \n\nإذاعة جيش العدو الإسرائيلي: مواجهة حصلت داخل مبنى صباح اليوم عندما تسللت مجموعة من وحدة إيغوز إلى داخله حينها فتح حزب الله النار وأطلق الصواريخ تجاه القوة، وحتى خلال عملية سحب الجرحى واصل حزب الله إطلاق النار والصواريخ.\n\n#الإعلام_الحربي"
    },
    {
      "time": "12:04",
      "summary": "وسائل إعلام إسرائيلية: منذ صباح اليوم حصلت عدة اشتباكات بين الجيش الإسرائيلي وعناصر حزب الله من مسافة قريبة في عدد من النقاط.",
      "fullText": "#إعلام_العدو \n\nوسائل إعلام إسرائيلية: منذ صباح اليوم حصلت عدة اشتباكات بين الجيش الإسرائيلي وعناصر حزب الله من مسافة قريبة في عدد من النقاط.\n\n#الإعلام_الحربي"
    },
    {
      "time": "13:10",
      "summary": "وسائل إعلام إسرائيلية: مجالس المستوطنات الإسرائيلية تنعى حتى الآن 4 جنود إسرائيليين قتلوا خلال المعارك مع حزب الله اليوم.",
      "fullText": "#إعلام_العدو \n\nوسائل إعلام إسرائيلية: مجالس المستوطنات الإسرائيلية تنعى حتى الآن 4 جنود إسرائيليين قتلوا خلال المعارك مع حزب الله اليوم.\n\n#الإعلام_الحربي"
    },
    {
      "time": "14:25",
      "summary": "المتحدث باسم جيش العدو الإسرائيلي: الإعلان عن مقتل 7 جنود إسرائيليين خلال المعارك مع حزب الله اليوم ليرتفع عدد القتلى المعلن عنهم إلى 8",
      "fullText": "#إعلام_العدو \n\nالمتحدث باسم جيش العدو الإسرائيلي: الإعلان عن مقتل 7 جنود إسرائيليين خلال المعارك مع حزب الله اليوم ليرتفع عدد القتلى المعلن عنهم إلى 8\n\n#الإعلام_الحربي"
    },
    {
      "time": "14:30",
      "summary": "المتحدث باسم جيش العدو الإسرائيلي: مقتل 8 ضباط وجنود وإصابة 7 آخرين بجروح خطيرة خلال المعارك مع حزب الله، حيث توزعت الإصابات بين لواء \"جولاني\" ووحدة \"إيغوز\".",
      "fullText": "#إعلام_العدو \n\nالمتحدث باسم جيش العدو الإسرائيلي: مقتل 8 ضباط وجنود وإصابة 7 آخرين بجروح خطيرة خلال المعارك مع حزب الله، حيث توزعت الإصابات بين لواء \"جولاني\" ووحدة \"إيغوز\".\n\n#الإعلام_الحربي"
    },
    {
      "time": "15:05",
      "summary": "إذاعة جيش العدو الإسرائيلي:\nقامت الفرقة 98، ومن ضمنها أيضًا وحدة إيغوز، بمناورة ليل الاثنين والثلاثاء، وبعد يوم واحد، في وقت مبكر من هذا الصباح، بدأت وحدة إيغوز في شن هجمات، ودخلت إحدى القوات إلى مبنى",
      "fullText": "#إعلام_العدو \n\nإذاعة جيش العدو الإسرائيلي:\nقامت الفرقة 98، ومن ضمنها أيضًا وحدة إيغوز، بمناورة ليل الاثنين والثلاثاء، وبعد يوم واحد، في وقت مبكر من هذا الصباح، بدأت وحدة إيغوز في شن هجمات، ودخلت إحدى القوات إلى مبنى في قرية جنوب لبنان، حيث واجهت حزب الله في معركة وجهاً لوجه، وبعد تلك المواجهة، بدأت سلسلة من المواجهات وإطلاق النار على القوات من اتجاهات مختلفة حيث أطلق العشرات من عناصر حزب الله صواريخ مضادة للدروع على القوات، وأُصيب نحو 30 مقاتلاً إسرائيليًا بجراح متفاوتة خلال المعركة، بينهم 5 إصابات خطيرة بالإضافة إلى القتلى.\n\n#الإعلام_الحربي"
    },
    {
      "time": "15:24",
      "summary": "صحيفة \"يديعوت أحرونوت\" العبرية: كارثة في المناورة البرية جنوب لبنان.",
      "fullText": "#إعلام_العدو\n\nصحيفة \"يديعوت أحرونوت\" العبرية: كارثة في المناورة البرية جنوب لبنان.\n\n#الإعلام_الحربي"
    },
    {
      "time": "15:33",
      "summary": "مستشفى \"زيف\" في صفد: استقبلنا اليوم 39 جنديًا إسرائيليًا مصابًا جراء المعارك جنوب لبنان.",
      "fullText": "#إعلام_العدو \n\nمستشفى \"زيف\" في صفد: استقبلنا اليوم 39 جنديًا إسرائيليًا مصابًا جراء المعارك جنوب لبنان.\n\n#الإعلام_الحربي"
    },
    {
      "time": "15:54",
      "summary": "إذاعة جيش العدو الإسرائيلي: \nمنذ بداية المناورة البرية في جنوب لبنان، قُتل 8 جنود وسقط عشرات الجرحى بينهم 7 إصاباتهم خطيرة.",
      "fullText": "#إعلام_العدو \n\nإذاعة جيش العدو الإسرائيلي: \nمنذ بداية المناورة البرية في جنوب لبنان، قُتل 8 جنود وسقط عشرات الجرحى بينهم 7 إصاباتهم خطيرة.\n\n#الإعلام_الحربي"
    },
    {
      "time": "17:13",
      "summary": "المتحدث باسم جيش العدو الإسرائيلي: إطلاق 100 صاروخ خلال الساعتين الماضيتين من لبنان.",
      "fullText": "#إعلام_العدو \n\nالمتحدث باسم جيش العدو الإسرائيلي: إطلاق 100 صاروخ خلال الساعتين الماضيتين من لبنان.\n\n#الإعلام_الحربي"
    },
    {
      "time": "17:35",
      "summary": "وسائل إعلام إسرائيلية: انقطاع التيار الكهربائي عن عدد من المستوطنات بالجليل الغربي جراء سقوط صواريخ أُطلقت من لبنان.",
      "fullText": "#إعلام_العدو \n\nوسائل إعلام إسرائيلية: انقطاع التيار الكهربائي عن عدد من المستوطنات بالجليل الغربي جراء سقوط صواريخ أُطلقت من لبنان.\n\n#الإعلام_الحربي"
    },
    {
      "time": "19:56",
      "summary": "صحيفة \"يديعوت أحرونوت\" العبرية - رون بن يشاي: تخشى القوات الميدانية الإسرائيلية من وضع قد تتعرض فيه للصواريخ المضادة للدروع، التي يعتبرها حزب الله السلاح الرئيسي.",
      "fullText": "#إعلام_العدو \n\nصحيفة \"يديعوت أحرونوت\" العبرية - رون بن يشاي: تخشى القوات الميدانية الإسرائيلية من وضع قد تتعرض فيه للصواريخ المضادة للدروع، التي يعتبرها حزب الله السلاح الرئيسي.\n\n#الإعلام_الحربي"
    }
  ],
  "iran": [
    {
      "time": "06:32",
      "source": "إيران",
      "summary": "بيانٌ صادرٌ عن القوات المسلحة اليمنية\n\nبسم الله الرحمن الرحيم\nقال تعالى: {یَـٰۤأَیُّهَا ٱلَّذِینَ ءَامَنُوۤا۟ إِن تَنصُرُوا۟ ٱللَّهَ یَنصُرۡكُمۡ وَیُثَبِّتۡ أَقۡدَامَكُمۡ } صدقَ اللهُ العظيم\n\nانتصارا ",
      "fullText": "بيانٌ صادرٌ عن القوات المسلحة اليمنية\n\nبسم الله الرحمن الرحيم\nقال تعالى: {یَـٰۤأَیُّهَا ٱلَّذِینَ ءَامَنُوۤا۟ إِن تَنصُرُوا۟ ٱللَّهَ یَنصُرۡكُمۡ وَیُثَبِّتۡ أَقۡدَامَكُمۡ } صدقَ اللهُ العظيم\n\nانتصارا لمظلومية الشعبين الفلسطيني واللبناني ودعما للمقاومتين الفلسطينية واللبنانية\nنفذت القوة الصاروخية في القوات المسلحة اليمنية عملية عسكرية استهدفتْ مواقع عسكرية في عمق الكيان الصهيوني في فلسطين المحتلة وذلك بثلاثة صواريخ مجنحة نوع قدس5\n\nوقدْ تمكنت الصواريخ من الوصول إلى أهدافها بنجاح وسط تكتم العدو عن نتائج العملية.\n\nإن القوات المسلحة اليمنية تبارك عملية الوعد الصادق الإيرانية الثانية ضد العدو الإسرائيلي وتؤكد استعدادها للمشاركة في أية عمليات عسكرية مشتركة ضد العدو الإسرائيلي انتصارا للشعبين الفلسطيني واللبناني وردا على أي عدوان إسرائيلي يطال جبهات الإسناد.\n\nوتؤكد القوات المسلحة اليمنية أن استمرار الدعم الأمريكي والبريطاني للعدو الإسرائيلي يضع المصالح الأمريكية والبريطانية في المنطقة تحت دائرة النار وأنها لن تتردد بعون الله تعالى في توسيع عملياتها العسكرية ضد العدو الإسرائيلي ومن يقف خلفه حتى وقف العدوان ورفع الحصار عن غزة وكذلك وقف العدوان على لبنان.\n\nوالله حسبنا ونعم الوكيل، نعم المولى ونعم النصير\n\nعاش اليمن حرا عزيزا مستقلا\nوالنصر لليمن ولكل أحرار الأمة\n\nصنعاء  29 ربيع أول 1446للهجرة\nالموافق للـ 2 أكتوبر 2024م\n\nصادرٌ عن القوات المسلحة اليمنية"
    },
    {
      "time": "16:16",
      "source": "إيران",
      "summary": "{فَإِذَا لَقِيتُمُ ٱلَّذِينَ كَفَرُواْ فَضَرْبَ ٱلرِّقَابِ حَتَّىٰٓ إِذَآ أَثْخَنتُمُوهُمْ فَشُدُّواْ ٱلْوَثَاقَ فَإِمَّا مَنًّۢا بَعْدُ وَإِمَّا فِدَآءً حَتَّىٰ تَضَعَ ٱلْحَرْبُ أَوْزَارَهَا}\n\nبيان",
      "fullText": "{فَإِذَا لَقِيتُمُ ٱلَّذِينَ كَفَرُواْ فَضَرْبَ ٱلرِّقَابِ حَتَّىٰٓ إِذَآ أَثْخَنتُمُوهُمْ فَشُدُّواْ ٱلْوَثَاقَ فَإِمَّا مَنًّۢا بَعْدُ وَإِمَّا فِدَآءً حَتَّىٰ تَضَعَ ٱلْحَرْبُ أَوْزَارَهَا}\n\nبيان عسكري صادر عن : \n... ::: كتائب الشهيد عز الدين القسام ::: ... \n\nتعلن كتائب الشهيد عز الدين القسام مسؤوليتها عن عملية \"يافا\" البطولية التي نفذها المجاهدان القساميان محمد راشد مسك  وأحمد عبد الفتاح الهيموني من مدينة الخليل، والتي أدت وفق اعتراف العدو إلى مقتل 7 صهاينةٍ وإصابة 16 آخرين بعضهم جراحه خطرة، وقد تزامنت العملية مع ضرباتٍ موجعةٍ تعرض لها قلب الكيان أمس الثلاثاء 28 ربيع الأول 1446 هـ الموافق 01/10/2024م، في ذروة استنفاره الأمني من مختلف جبهات المقاومة، اختتمت بالهجوم الصاروخي الكبير الذي نفذته إيران في عملية \"الوعد الصادق2\". \n\nوفي تفاصيل العملية القسامية فقد تمكن مجاهدانا من التسلل إلى داخل أراضينا المحتلة، وطعن أحد جنود الاحتلال والاستيلاء على سلاحه الآلي، ثم تنفيذ العملية البطولية في موقعين مختلفين في قلب (تل أبيب) أحدهما داخل محطة للقطارات، وقاموا بالإجهاز على المغتصبين الصهاينة من مسافة صفر. \n\nوإن كتائب القسام وهي تعلن مسؤوليتها عن هذه العملية النوعية لتقول للمحتلين: إن قادم الأيام ستحمل في طياتها موتًا سيأتيكم من مختلف مناطق الضفة، على أيدي مجاهدينا الأشداء من أبناء القائدين إسماعيل هنية وصالح العاروري، والذين نُعدُّهم ونجهزهم ليخطّوا ببطولاتهم صفحات عزٍ في معركة طوفان الأقصى ستثلج صدور أبناء شعبنا بعون الله، وطالما واصل الاحتلال إبادة شعبنا وأطفالنا في غزة فإنه سيعتاد رؤية قتلاه في شوارع مدننا المحتلة بإذن الله.\n\nوإنه لجهاد نصر أو استشهاد،،، \nكتائب الشهيد عز الدين القسام – فلسطين\nالأربعاء 29 ربيع الأول 1446 هـ \nالموافق02/10/2024م"
    }
  ],
  "videos": [],
  "allies": [
    {
      "flag": "اليمن",
      "time": "06:33",
      "summary": "بيان القوات المسلحة اليمنية بشأن استهداف أهداف حيوية في عمق الكيان الصهيوني في فلسطين المحتلة بثلاثة صواريخ مجنحة نوع قدس5 حققت أهدافها بنجاح وسط تكتم العدو عن نتائج العملية - 2 أكتوبر 2024م\n\nwww.mmy.",
      "fullText": "بيان القوات المسلحة اليمنية بشأن استهداف أهداف حيوية في عمق الكيان الصهيوني في فلسطين المحتلة بثلاثة صواريخ مجنحة نوع قدس5 حققت أهدافها بنجاح وسط تكتم العدو عن نتائج العملية - 2 أكتوبر 2024م\n\nwww.mmy.ye/325980"
    }
  ]
}